boxmox/.gitignore
boxmox/__init__.py
boxmox/data.py
boxmox/experiment.py
boxmox/fluxes.py
boxmox/plotter.py
boxmox-1.2.5.dist-info/LICENSE
boxmox-1.2.5.dist-info/WHEEL
boxmox-1.2.5.dist-info/METADATA
boxmox-1.2.5.dist-info/RECORD
