Metadata-Version: 2.1
Name: boxmox
Version: 1.2.5
Summary: BOXMOX python interface
Home-page: https://mbees.med.uni-augsburg.de/
License: GPL-3.0-or-later
Keywords: atmosphere,chemistry,box model,boxmox
Author: Christoph Knote
Author-email: christoph.knote@med.uni-augsburg.de
Requires-Python: >=3,<4
Classifier: Development Status :: 5 - Production/Stable
Classifier: Environment :: Console
Classifier: Intended Audience :: Developers
Classifier: Intended Audience :: Education
Classifier: Intended Audience :: End Users/Desktop
Classifier: Intended Audience :: Science/Research
Classifier: License :: OSI Approved :: GNU General Public License v3 (GPLv3)
Classifier: License :: OSI Approved :: GNU General Public License v3 or later (GPLv3+)
Classifier: Operating System :: POSIX
Classifier: Programming Language :: Python :: 3
Classifier: Programming Language :: Python :: 3.10
Classifier: Programming Language :: Python :: 3.4
Classifier: Programming Language :: Python :: 3.5
Classifier: Programming Language :: Python :: 3.6
Classifier: Programming Language :: Python :: 3.7
Classifier: Programming Language :: Python :: 3.8
Classifier: Programming Language :: Python :: 3.9
Classifier: Topic :: Education
Classifier: Topic :: Scientific/Engineering
Classifier: Topic :: Utilities
Requires-Dist: f90nml (>=1.3)
Requires-Dist: numpy (>=1.2)
Requires-Dist: pyparsing (>=3)
Project-URL: Repository, https://mbees.med.uni-augsburg.de/gitlab/mbees/boxmox_pypackage
Project-URL: issues, http://mbees.med.uni-augsburg.de/gitlab/mbees/boxmox_pypackage/issues
